{
  "type": "minecraft:generic",
  "pools": [
    {
      "rolls": 1,
      "entries": [
        {
          "type": "minecraft:item",
          "name": "minecraft:paper",
          "functions": [
            {
              "function": "minecraft:set_name",
              "name": [
                {"text": "前ページへ","italic": false,"color": "white"}
              ]
            },
            {
              "function": "minecraft:set_nbt",
              "tag": "{HideFlags:61,gui_item:1,CustomModelData:4}"
            }
          ]
        }
      ]
    }
  ]
}